{"сообщить": 211116, "сообщать": 456884, "задержать": 118065, "пройти": 94201, "найти": 74305, "провести": 112357, "пострадать": 45580, "погибнуть": 82862, "принять": 142818, "подозревать": 52701, "появиться": 72856, "начать": 86245, "решить": 66664, "удаться": 67222, "сделать": 79533, "грозить": 17215, "начаться": 64193, "судить": 13915, "признать": 68779, "проходить": 55496, "ждать": 13666, "проводить": 37063, "прийтись": 33193, "пытаться": 46036, "помочь": 29269, "скончаться": 26167, "обвинять": 42223, "упасть": 32392, "запретить": 52581, "просить": 18357, "украсть": 11952, "похитить": 21241, "хотеть": 45137, "добавить": 61704, "организовать": 29208, "пояснить": 36121, "считать": 85831, "врезаться": 8653, "увидеть": 17052, "написать": 41957, "искать": 12617, "создать": 67148, "осудить": 26429, "спасти": 13305, "стоить": 33307, "предложить": 64861, "продолжаться": 23119, "продолжать": 22695, "писать": 91141, "вести": 41890, "принимать": 36518, "загореться": 7008, "использовать": 56159, "прийти": 17430, "поймать": 8716, "подписать": 48247, "обещать": 14814, "ударить": 8359, "построить": 29951, "устроить": 18886, "делать": 25754, "отказаться": 71110, "убить": 16372, "привлечь": 20488, "предлагать": 26011, "избить": 8278, "прокомментировать": 17095, "попросить": 27362, "ликвидировать": 10931, "остановить": 15773, "позволить": 35452, "угрожать": 13944, "следовать": 26433, "умереть": 15692, "напасть": 12790, "разыскивать": 5380, "арестовать": 37887, "продолжить": 19261, "видеть": 19326, "потратить": 14742, "приговорить": 29012, "повредить": 10108, "требовать": 33680, "закрыть": 13006, "поздравить": 4201, "превысить": 16185, "увеличить": 22520, "попытаться": 20703, "закончиться": 10540, "выиграть": 26277, "поддержать": 25548, "помогать": 10767, "достигнуть": 31627, "потерять": 18379, "оценить": 18070, "завершиться": 22606, "ограбить": 4582, "родиться": 10780, "увеличиться": 18585, "угнать": 3842, "объяснить": 26827, "утвердить": 15916, "перекрыть": 7078, "предупреждать": 4991, "потребовать": 31997, "представлять": 32053, "рекомендовать": 9340, "воспользоваться": 8442, "призвать": 31690, "позволять": 25648, "забить": 15094, "соблюдать": 3872, "заболеть": 2473, "уничтожить": 16499, "пользоваться": 15416, "бороться": 11392, "надеяться": 14711, "призывать": 9720, "допустить": 17733, "возникнуть": 17507, "пообещать": 30534, "подвести": 3215, "обязать": 15861, "запустить": 20833, "нападать": 20751, "решаться": 4815, "приостановить": 14507, "победить": 16786, "снизиться": 16696, "нарушить": 10853, "лишиться": 8261, "завоевать": 9619, "начинать": 13724, "вспыхнуть": 2200, "остановиться": 5763, "утверждать": 51883, "приступить": 10734, "опуститься": 6948, "приходить": 5155, "подарить": 5378, "образоваться": 6351, "приходиться": 12563, "снизить": 14843, "понять": 9445, "обмануть": 2933, "вытащить": 2465, "разрешить": 19070, "согласиться": 20568, "прекратить": 24045, "потребоваться": 8301, "сократить": 16030, "произвести": 12463, "освободить": 21059, "поддерживать": 19529, "создавать": 11876, "схватить": 2864, "разбить": 3688, "отравиться": 2165, "проникнуть": 6019, "пожаловаться": 8140, "сломать": 3972, "превышать": 17374, "бросить": 7648, "выпустить": 36260, "вывести": 14781, "проиграть": 13275, "обрушиться": 5864, "обвинить": 35477, "забросить": 7092, "договориться": 15990, "строить": 7629, "добиться": 15447, "обокрасть": 1193, "жаловаться": 4749, "подорожать": 9218, "понадобиться": 4261, "предупредить": 9467, "поблагодарить": 3996, "сократиться": 11646, "наказать": 5827, "закончить": 7271, "наступить": 3317, "перестать": 7509, "понимать": 8618, "провалиться": 2487, "разбираться": 1804, "повысить": 10715, "зарезать": 1759, "исчезнуть": 4897, "требоваться": 5542, "советовать": 1978, "объединить": 16624, "заслужить": 2874, "обновить": 6442, "решать": 6020, "застрелить": 12048, "выстрелить": 5028, "усилить": 5798, "присвоить": 5813, "желать": 4325, "украсить": 2705, "рассчитывать": 14002, "одобрить": 18826, "наехать": 1153, "выгореть": 1072, "нарушать": 8332, "страдать": 6919, "заблокировать": 9657, "заставить": 9035, "забыть": 2888, "спрятать": 3016, "комментировать": 16782, "достигать": 9430, "наступать": 1724, "начинаться": 4675, "везти": 2128, "пресечь": 2811, "изнасиловать": 2355, "обыграть": 10974, "нуждаться": 4198, "любить": 4834, "оценивать": 8445, "охранять": 4290, "сформировать": 8864, "способствовать": 8360, "мешать": 4765, "продолжиться": 3830, "пожелать": 4141, "верить": 4573, "возобновить": 9388, "отказать": 9998, "стрелять": 6686, "потерпеть": 6942, "потеплеть": 458, "достать": 2593, "стараться": 3752, "поссориться": 1372, "чувствовать": 5696, "приниматься": 4277, "спровоцировать": 5592, "разобраться": 4131, "вынудить": 12611, "ворваться": 4352, "переть": 707, "появляться": 10532, "помнить": 2524, "производить": 8145, "изучить": 6195, "развиваться": 3962, "привлекать": 4979, "бить": 3712, "понравиться": 3474, "защищать": 7401, "посчитать": 6659, "болеть": 1634, "поздравлять": 968, "изготовить": 4789, "почувствовать": 2931, "подключить": 2906, "запрещать": 7576, "развивать": 6622, "защитить": 8906, "отрицать": 8282, "востребовать": 2296, "применить": 7974, "хватать": 3553, "захватить": 19525, "избивать": 2756, "добавлять": 5815, "обжаловать": 7323, "взломать": 3613, "наброситься": 1455, "употреблять": 3141, "сработать": 4477, "заподозрить": 8023, "отказываться": 11036, "затормозить": 811, "возникать": 5194, "предотвратить": 6066, "придумать": 4101, "вспомнить": 2685, "помешать": 6058, "отбросить": 878, "угодить": 640, "держаться": 2509, "бояться": 3957, "пояснять": 3638, "уменьшиться": 3970, "возвести": 4371, "сотрудничать": 9395, "рисковать": 1765, "повезти": 1230, "изучать": 5489, "задеть": 2133, "выручить": 3980, "скрыть": 2297, "броситься": 1634, "улучшить": 5019, "разрушить": 7486, "ловить": 1336, "прорвать": 1360, "устраивать": 5053, "разгромить": 3757, "забывать": 1148, "травмировать": 1045, "увеличиваться": 3145, "разыскать": 876, "падать": 4267, "радовать": 511, "повыситься": 2303, "испугаться": 1567, "закрывать": 2766, "порадовать": 531, "расстрелять": 4905, "развернуться": 1822, "объяснять": 7727, "распорядиться": 3645, "взорвать": 8884, "находить": 3210, "возлюбить": 1468, "взяться": 1931, "сломаться": 998, "постановить": 5615, "возобновиться": 3615, "обворовать": 349, "лидировать": 6564, "сэкономить": 2828, "стремиться": 4899, "запускать": 2180, "подъехать": 1761, "захотеть": 3625, "усилиться": 1349, "презентовать": 1191, "постараться": 2125, "применять": 5691, "спасать": 1400, "заказать": 5413, "основать": 20216, "приняться": 1472, "тратить": 3717, "предпринять": 7360, "опасаться": 8058, "останавливаться": 1494, "сорвать": 5001, "решиться": 2867, "атаковать": 6501, "дарить": 850, "обойти": 3360, "повышать": 3063, "сразиться": 684, "обстрелять": 7208, "поверить": 2156, "заканчиваться": 2525, "выпускать": 9041, "научить": 1848, "родить": 2186, "зажечь": 900, "удариться": 1005, "завладеть": 1417, "выгнать": 1745, "посоветовать": 5085, "заинтересоваться": 3057, "информировать": 2242, "терять": 3191, "воровать": 1044, "душить": 1681, "проигнорировать": 2116, "спасть": 1371, "доложить": 1851, "проникать": 1390, "последовать": 7537, "удаваться": 4296, "проанализировать": 3757, "испортить": 1586, "украшать": 837, "признавать": 5888, "чаять": 769, "учить": 1335, "вырастить": 2528, "допускать": 3962, "предпочитать": 3592, "курировать": 3371, "раскаяться": 695, "раскритиковать": 6513, "ужесточить": 3173, "поразить": 3943, "напугать": 1440, "разрешать": 3100, "злоупотреблять": 919, "подводить": 641, "толкнуть": 912, "нравиться": 3003, "уменьшить": 3698, "прервать": 5060, "похоронить": 2670, "добиваться": 6929, "побороться": 1662, "патрулировать": 1431, "настроить": 3415, "догнать": 1495, "формировать": 2265, "прихватить": 381, "побить": 3000, "одолеть": 613, "благодарить": 669, "похищать": 1095, "снижаться": 3738, "укрепить": 2224, "скорбеть": 399, "инициировать": 4936, "пасть": 1231, "вспоминать": 1364, "завязаться": 1519, "пригрозить": 6726, "отвести": 2942, "прятать": 757, "поведать": 1092, "отражать": 3218, "проинформировать": 2696, "сбросить": 2273, "опускаться": 1004, "приветствовать": 2360, "обчистить": 177, "ухудшиться": 2436, "прибавить": 1767, "доверять": 2083, "понизиться": 981, "прекратиться": 2420, "застать": 863, "заминировать": 2334, "отслеживать": 2537, "отклонить": 7966, "исследовать": 3581, "увеличивать": 2881, "скрывать": 3237, "завершаться": 1097, "поругаться": 280, "выдворить": 1165, "обезвредить": 2656, "надругаться": 314, "расправиться": 748, "завысить": 2097, "снижать": 2595, "раздавить": 465, "грабить": 653, "зацепить": 381, "интересоваться": 2437, "повышаться": 1298, "гордиться": 1340, "останавливать": 1016, "заехать": 578, "объединять": 4002, "обманывать": 716, "хорошеть": 1223, "творить": 423, "выслать": 3096, "обходить": 692, "заставлять": 3383, "шокировать": 1501, "дисквалифицировать": 3593, "улучшиться": 1307, "придерживаться": 4030, "оправдать": 5082, "колебаться": 1650, "обеспокоить": 2151, "прекращаться": 1211, "предпринимать": 3135, "опередить": 2935, "отомстить": 1701, "насиловать": 741, "освоить": 1017, "игнорировать": 1623, "радоваться": 516, "пошутить": 1518, "возводить": 1088, "модернизировать": 1728, "умирать": 1533, "убивать": 3509, "полагаться": 1409, "привыкнуть": 1091, "кинуться": 227, "скатиться": 320, "спастись": 1605, "блокировать": 6939, "проложить": 1230, "сомневаться": 2544, "экономить": 1222, "бросать": 2017, "выращивать": 924, "уклоняться": 844, "поинтересоваться": 1320, "оскорбить": 2057, "присудить": 3024, "организовывать": 1398, "протестовать": 8263, "вызволить": 421, "отыскать": 953, "высылать": 592, "опережать": 2270, "преследовать": 3635, "шутить": 808, "образовать": 3970, "преобладать": 799, "волновать": 761, "доставать": 454, "счесть": 10402, "разворачиваться": 2602, "уличить": 3922, "бушевать": 381, "противоречить": 4221, "достроить": 915, "перекрывать": 562, "инвестировать": 3715, "смять": 169, "сражаться": 2459, "обогнать": 2111, "ругаться": 529, "утратить": 2453, "изготавливать": 816, "разозлиться": 411, "воспринять": 2438, "уважать": 1863, "укреплять": 863, "отстоять": 1014, "задерживать": 2553, "утащить": 260, "проследить": 1128, "просмотреть": 1079, "противостоять": 2788, "переиграть": 2195, "осложнить": 1047, "тормозить": 495, "осветить": 477, "разъяснить": 1486, "побеждать": 2250, "заливать": 296, "пугать": 920, "ослабить": 1282, "отразить": 2347, "отступать": 501, "оскорблять": 2167, "повесить": 1184, "уложить": 498, "задохнуться": 358, "загрязнять": 465, "предпочесть": 2636, "перепугать": 189, "критиковать": 3677, "спалить": 152, "красть": 564, "сопротивляться": 768, "звереть": 679, "выловить": 501, "царить": 499, "осуждать": 1702, "подписывать": 2183, "портить": 607, "анализировать": 1925, "осваивать": 660, "обезопасить": 673, "обгонять": 344, "вытаскивать": 311, "договариваться": 1137, "осознать": 1100, "воссоздать": 1095, "препятствовать": 3278, "отрезать": 1581, "подорвать": 3491, "сокращать": 1854, "генерировать": 932, "уклониться": 585, "сокращаться": 1643, "покорить": 604, "повздорить": 262, "оккупировать": 2776, "выигрывать": 2937, "освобождать": 1067, "браться": 792, "задавить": 490, "подкупить": 433, "отступить": 897, "сторожить": 322, "смягчить": 1634, "беречь": 249, "забивать": 753, "зарубить": 251, "вступиться": 1210, "выкрасть": 419, "накинуться": 187, "соорудить": 745, "инкриминировать": 1747, "ценить": 784, "возрастать": 1104, "оптимизировать": 779, "порекомендовать": 1305, "осознавать": 781, "уведомить": 2733, "выработать": 2045, "тащить": 251, "проигрывать": 1581, "удвоить": 1271, "захватывать": 988, "отвергнуть": 6361, "уничтожать": 1769, "свалиться": 355, "посетовать": 1919, "употребить": 544, "понижаться": 185, "оборваться": 299, "упустить": 1406, "молиться": 1060, "изложить": 2559, "развращать": 111, "дорожать": 901, "воевать": 3611, "депортировать": 2017, "прекращать": 1928, "распоряжаться": 926, "терпеть": 1519, "заслуживать": 1809, "учредить": 3737, "увлекаться": 806, "развести": 617, "отстаивать": 1881, "покорёжить": 117, "приказать": 3023, "покалечить": 176, "финансировать": 3255, "усиливаться": 579, "рождаться": 466, "разбушеваться": 148, "израсходовать": 962, "обвалиться": 1132, "оповестить": 623, "улучшать": 601, "вдохновить": 1478, "исчезать": 861, "негодовать": 154, "встревожить": 334, "настать": 693, "грозиться": 356, "отследить": 731, "разглядеть": 907, "взламывать": 391, "разразиться": 1415, "обрадоваться": 323, "обновлять": 614, "прострелить": 384, "беспокоиться": 737, "улыбаться": 618, "окончиться": 553, "подтолкнуть": 773, "толкать": 450, "тянуть": 455, "содействовать": 1071, "помиловать": 1401, "присматривать": 320, "усиливать": 968, "настигнуть": 308, "приступать": 607, "переставать": 648, "сожалеть": 1272, "рожать": 345, "плакать": 716, "враждовать": 678, "волноваться": 445, "уменьшаться": 904, "донести": 685, "искорёжить": 155, "покорять": 159, "наращивать": 1125, "придумывать": 461, "преподавать": 1186, "эксплуатировать": 971, "потянуть": 280, "осложнять": 528, "воспринимать": 1848, "издеваться": 739, "похвастаться": 619, "взволновать": 294, "сбрасывать": 629, "обидеться": 604, "ломать": 692, "подключать": 385, "объединиться": 2003, "прибавиться": 268, "проконсультироваться": 299, "пропагандировать": 1098, "руководствоваться": 1723, "ссориться": 235, "наслаждаться": 372, "погубить": 332, "занизить": 1571, "велеть": 881, "приревновать": 96, "спасаться": 667, "приостанавливать": 845, "жалеть": 476, "одобрять": 1334, "навредить": 683, "провоцировать": 1302, "ослабнуть": 378, "расширяться": 727, "нарастить": 1375, "избавить": 1138, "смеяться": 747, "поощрить": 246, "отказывать": 1301, "укрепиться": 1005, "разложить": 257, "развить": 710, "пресекать": 580, "добить": 357, "почитать": 463, "загрязнить": 619, "вызволять": 100, "пренебрегать": 281, "расстроить": 942, "присваивать": 533, "заколоть": 161, "обстреливать": 1041, "заступиться": 594, "задыхаться": 167, "отбить": 1955, "кончиться": 401, "насладиться": 196, "сочувствовать": 467, "поспособствовать": 744, "освещать": 1575, "конфликтовать": 780, "профинансировать": 1315, "усугубить": 499, "перерезать": 632, "тлеть": 122, "отогнать": 505, "развозить": 219, "травить": 359, "вломиться": 213, "выследить": 346, "приглянуться": 133, "зажигать": 175, "оправдывать": 784, "потрясти": 469, "преступить": 114, "перехватить": 1960, "потрясать": 462, "награбить": 170, "урезать": 1288, "понизить": 2547, "дружить": 508, "разрушать": 887, "сплотить": 234, "соглашаться": 1156, "разъяснять": 358, "сетовать": 345, "улыбнуться": 168, "возобновлять": 947, "вешать": 258, "угонять": 179, "обязывать": 1966, "лишаться": 549, "усмотреть": 1108, "драться": 1291, "изуродовать": 254, "похвалить": 1073, "разрешаться": 1128, "выдумать": 502, "подрывать": 920, "консультировать": 600, "рискнуть": 221, "подъезжать": 250, "поражать": 1559, "беспокоить": 1217, "нервничать": 323, "срывать": 470, "шантажировать": 476, "отловить": 162, "спугнуть": 148, "подсказать": 263, "гнать": 164, "пожалеть": 498, "отбиться": 355, "обворовывать": 81, "оговорить": 1203, "расстроиться": 268, "унижать": 635, "усомниться": 1845, "завоёвывать": 556, "разбивать": 362, "окружить": 2355, "окрепнуть": 122, "проесть": 133, "кинуть": 511, "отравить": 1924, "усовершенствовать": 1473, "вынуждать": 776, "адаптироваться": 559, "завышать": 389, "давить": 662, "расшириться": 425, "пытать": 958, "ужесточать": 899, "соболезновать": 91, "проучить": 119, "докладывать": 382, "первенствовать": 305, "красить": 247, "известить": 801, "устраняться": 111, "выпалить": 240, "совершенствовать": 298, "подкинуть": 164, "субсидировать": 428, "понаблюдать": 214, "рапортовать": 157, "выгонять": 274, "привыкать": 185, "разгадать": 204, "укрепляться": 556, "уведомлять": 530, "исправиться": 149, "увлечься": 408, "разочаровать": 1312, "повелеть": 268, "затратить": 642, "подыскивать": 333, "навязать": 472, "винить": 703, "отвергать": 3613, "кидать": 543, "запугать": 579, "сотворить": 121, "пуститься": 174, "побудить": 790, "постичь": 336, "штурмовать": 787, "обрадовать": 203, "ухудшаться": 771, "облагородить": 67, "испугать": 227, "перебить": 316, "отравлять": 1094, "соблюсти": 547, "огорчить": 327, "впечатлить": 232, "отблагодарить": 165, "подбросить": 646, "скатываться": 113, "превосходить": 1525, "подставить": 491, "развиться": 472, "прокладывать": 203, "приостанавливаться": 384, "впечатлять": 107, "доминировать": 1262, "порочить": 1020, "ратифицировать": 1783, "озаботить": 629, "укоротить": 609, "поощрять": 591, "оборвать": 195, "деформировать": 227, "посмеяться": 646, "улучшаться": 391, "своровать": 59, "надоесть": 425, "забеспокоиться": 97, "ухудшить": 851, "извещать": 167, "переболеть": 63, "резать": 275, "откопать": 176, "бросаться": 303, "рассыпаться": 156, "поладить": 112, "нейтрализовать": 755, "раздражать": 674, "догонять": 163, "вредить": 649, "стучать": 252, "исчерпать": 1120, "подпортить": 69, "баловать": 47, "загнать": 409, "взрывать": 453, "хоронить": 446, "прижиться": 141, "заесть": 465, "оповещать": 248, "образовываться": 333, "парировать": 384, "тревожить": 199, "совершенствоваться": 138, "отчаяться": 182, "врать": 329, "затеять": 351, "наставить": 81, "захоронить": 983, "обыгрывать": 314, "озаботиться": 394, "утерять": 804, "крепчать": 34, "кидаться": 133, "присмотреть": 149, "зародиться": 354, "оклеветать": 170, "выручать": 101, "изувечить": 70, "таскать": 177, "загрызть": 289, "одарить": 70, "санкционировать": 2256, "припомнить": 347, "славить": 51, "глумиться": 78, "поискать": 236, "предотвращать": 533, "паниковать": 146, "недоумевать": 207, "достраивать": 144, "полюбить": 303, "предостерегать": 261, "терроризировать": 263, "перемёрзнуть": 24, "угадать": 404, "упрекнуть": 962, "уменьшать": 658, "теплеть": 36, "вторгнуться": 985, "подбить": 496, "изгонять": 127, "хвастаться": 233, "отлавливать": 139, "доносить": 170, "превалировать": 126, "припрятать": 45, "чуять": 84, "пугаться": 75, "прибавлять": 136, "побояться": 267, "ущемлять": 517, "превзойти": 1310, "выслеживать": 196, "набить": 202, "ругать": 210, "грянуть": 34, "переоценить": 384, "отругать": 90, "разнести": 216, "замучить": 163, "расплакаться": 244, "обкрадывать": 30, "палить": 67, "проиллюстрировать": 321, "предостеречь": 1036, "испортиться": 323, "поколотить": 35, "рваться": 227, "выкопать": 272, "побаловать": 30, "позавидовать": 94, "скандалить": 60, "облюбовать": 82, "разминировать": 239, "разогнать": 2370, "укрыть": 110, "форсировать": 326, "навязывать": 464, "повредиться": 59, "завязать": 516, "колотить": 53, "прибавляться": 52, "недооценить": 505, "разжигать": 447, "материться": 125, "расстраиваться": 87, "усугублять": 265, "обчищать": 26, "ослабеть": 107, "разругаться": 53, "расколоть": 389, "подталкивать": 275, "разворотить": 42, "подсказывать": 168, "объединяться": 596, "понижать": 339, "разгневать": 288, "сечь": 76, "обидеть": 495, "дискредитировать": 938, "разоблачить": 882, "отвоевать": 222, "нагреть": 195, "сбавить": 95, "посеять": 1051, "утроить": 136, "развалиться": 653, "подложить": 250, "громить": 358, "всколыхнуть": 51, "занижать": 300, "побуждать": 255, "обосноваться": 480, "отгонять": 125, "арестовывать": 905, "сбавлять": 45, "раскаиваться": 260, "перегнать": 153, "вырабатывать": 854, "окружать": 429, "ассистировать": 398, "преуспеть": 194, "порадоваться": 220, "пострелять": 109, "растерять": 193, "иллюстрировать": 406, "обожать": 206, "осадить": 488, "занервничать": 39, "врываться": 178, "наладиться": 91, "расцвести": 46, "сузить": 123, "крушить": 150, "осваиваться": 73, "спаивать": 61, "выдворять": 134, "ослаблять": 261, "симпатизировать": 293, "гнить": 104, "смягчать": 151, "поправиться": 261, "отпугивать": 230, "ударять": 106, "унизить": 331, "поболеть": 53, "благословить": 307, "довериться": 86, "обижать": 174, "страховать": 313, "прерывать": 491, "углубить": 89, "запугивать": 318, "втягиваться": 79, "подкупать": 152, "рассвирепеть": 27, "врезать": 50, "подружиться": 341, "созреть": 78, "нормализовать": 263, "грешить": 62, "лупить": 55, "умолять": 128, "отбиваться": 146, "мучить": 196, "щадить": 135, "обезоружить": 162, "упереться": 63, "упускать": 139, "вдохновлять": 375, "вдохновиться": 175, "докатиться": 59, "консультироваться": 290, "пренебречь": 218, "вспылить": 42, "потрепать": 87, "портиться": 111, "преступать": 43, "проспать": 154, "обживаться": 18, "отговорить": 212, "реветь": 69, "взбунтоваться": 289, "побеспокоиться": 28, "возобновляться": 239, "вымереть": 563, "отодвинуть": 347, "отрыть": 85, "снискать": 198, "выискивать": 64, "укрывать": 231, "побороть": 246, "обострять": 149, "изыскать": 229, "экстрадировать": 550, "соблазнить": 120, "обвести": 91, "поберечь": 41, "отчитать": 181, "перепугаться": 56, "прогнать": 657, "обезглавить": 882, "подсунуть": 50, "сузиться": 62, "хлопать": 133, "запаниковать": 120, "подвигнуть": 123, "увенчать": 87, "изобличить": 221, "принуждать": 493, "прогрессировать": 227, "заплакать": 126, "испачкать": 154, "сгнить": 67, "посоветоваться": 235, "воспроизвести": 502, "откапывать": 28, "дрожать": 101, "сокрыть": 38, "аплодировать": 198, "растратить": 177, "зреть": 53, "переборщить": 44, "сокрушаться": 86, "приспособиться": 226, "сужать": 70, "трястись": 79, "обогатить": 550, "потревожить": 81, "господствовать": 112, "истощить": 78, "надумать": 40, "тормознуть": 13, "отрапортовать": 74, "загораться": 81, "бомбить": 578, "застукать": 43, "натравить": 103, "отбивать": 172, "истребить": 200, "утаить": 123, "деформироваться": 91, "униматься": 25, "ломиться": 87, "насолить": 40, "опустошить": 194, "посочувствовать": 95, "казнить": 2823, "сочинять": 196, "дестабилизировать": 883, "развратить": 33, "распять": 155, "разжечь": 148, "порождать": 337, "повреждать": 150, "упираться": 108, "искусить": 52, "мстить": 425, "грызть": 72, "популяризировать": 137, "отучиться": 47, "цениться": 172, "расходовать": 478, "срастись": 87, "подыскать": 379, "упрекать": 487, "вторгаться": 267, "трактовать": 384, "грустить": 41, "прогнить": 62, "вытеснить": 1116, "браниться": 39, "выздоравливать": 84, "нагнать": 103, "отрывать": 101, "посодействовать": 205, "оберегать": 119, "поглумиться": 46, "мочить": 299, "поклясться": 331, "разукрасить": 46, "принудить": 447, "вышвырнуть": 73, "прохудиться": 24, "искоренить": 235, "вылавливать": 71, "воссоздавать": 135, "поломать": 135, "недооценивать": 247, "бунтовать": 120, "породить": 557, "разгадывать": 48, "раскопать": 264, "соврать": 97, "надуть": 72, "избавлять": 111, "завидовать": 141, "почуять": 34, "подставлять": 108, "восторжествовать": 119, "извинить": 251, "сплотиться": 178, "приживаться": 31, "наезжать": 40, "нагонять": 36, "расколоться": 242, "калечить": 56, "влюбиться": 207, "износиться": 27, "соблазниться": 12, "спонсировать": 620, "преувеличить": 360, "слабеть": 176, "понервничать": 28, "кануть": 41, "подкосить": 36, "кончаться": 118, "обрываться": 85, "озвереть": 16, "капать": 56, "раскручивать": 99, "оскорбиться": 42, "санировать": 109, "освежить": 51, "пресекаться": 163, "усматривать": 263, "выругаться": 158, "крепнуть": 40, "расшатать": 89, "противодействовать": 489, "софинансировать": 38, "прогонять": 72, "карать": 126, "приглядеть": 10, "ударяться": 51, "ненавидеть": 672, "присуждать": 670, "надлежать": 221, "наговорить": 52, "раскрутить": 136, "приглядывать": 33, "накапать": 13, "затребовать": 418, "злиться": 106, "разволноваться": 22, "польстить": 97, "воспрепятствовать": 806, "рассориться": 66, "углубиться": 108, "ныть": 24, "расквитаться": 13, "изыскивать": 105, "колоть": 104, "освоиться": 91, "углубляться": 86, "заступаться": 44, "ввергнуть": 73, "рассердиться": 66, "загубить": 29, "урезонить": 42, "воспроизводить": 693, "проинвестировать": 77, "забрасывать": 839, "освистать": 254, "воссоединиться": 872, "демонизировать": 75, "разграбить": 556, "продуть": 27, "проклинать": 57, "дурить": 22, "обнадёжить": 58, "вышибать": 45, "скулить": 25, "огорчать": 81, "погнать": 50, "бастовать": 922, "удлинить": 64, "приостановиться": 97, "вразумить": 24, "обличать": 77, "рассердить": 191, "ущемить": 183, "морочить": 20, "углублять": 41, "отговаривать": 69, "запрятать": 20, "побаиваться": 21, "недоглядеть": 8, "удвоиться": 464, "злить": 41, "изловить": 86, "запачкать": 62, "обеспокоиться": 208, "сопереживать": 53, "стращать": 13, "расправляться": 121, "оскудеть": 9, "точить": 20, "вериться": 44, "свергнуть": 2158, "сближаться": 127, "оттачивать": 33, "припугнуть": 76, "постигать": 34, "шлифовать": 22, "поволноваться": 13, "бездействовать": 159, "пенять": 26, "подговорить": 62, "затмить": 81, "грипповать": 6, "перегореть": 37, "выздороветь": 225, "дозволить": 89, "истолковать": 373, "сгладить": 195, "спадать": 95, "пускаться": 58, "жаждать": 138, "вспыхивать": 121, "засомневаться": 109, "сужаться": 49, "воздвигнуть": 215, "поправляться": 60, "зарождаться": 115, "выпроводить": 57, "взбеситься": 55, "обезвреживать": 102, "томиться": 26, "растлить": 45, "сочинить": 368, "рыдать": 73, "усваивать": 58, "встревожиться": 17, "застопорить": 27, "подстроиться": 41, "унывать": 25, "подшутить": 165, "нагнетать": 207, "обзывать": 133, "разгонять": 536, "взбудоражить": 63, "срастаться": 13, "пресмыкаться": 332, "лгать": 409, "агитировать": 411, "взбесить": 93, "царствовать": 45, "угнетать": 109, "прорывать": 56, "отчаиваться": 42, "выкроить": 18, "истребовать": 157, "разобщать": 15, "сгенерировать": 137, "пришить": 115, "дискриминировать": 190, "попрать": 53, "сколотить": 73, "запятнать": 141, "гадить": 29, "наврать": 17, "удобрять": 22, "порицать": 35, "обозвать": 295, "истерзать": 13, "облагораживать": 22, "умертвить": 138, "ублажить": 11, "осквернить": 730, "подразнить": 13, "вытряхивать": 8, "разрыдаться": 68, "созревать": 40, "сблизиться": 207, "обесчестить": 17, "исправляться": 45, "одолевать": 35, "солгать": 136, "всполошиться": 11, "подстраховать": 22, "избаловать": 33, "прикончить": 40, "смазать": 81, "рождать": 60, "вышибить": 19, "умножать": 28, "заклевать": 17, "расстреливать": 453, "развалить": 171, "отмести": 51, "отвадить": 43, "переплюнуть": 23, "разорить": 214, "рушить": 56, "консолидировать": 575, "клясться": 194, "пощадить": 74, "сконструировать": 495, "изгнать": 876, "опустошать": 39, "преподать": 97, "сдобрить": 13, "убиваться": 14, "вытеснять": 230, "обнадёживать": 144, "подступать": 13, "отрезвить": 15, "раздражить": 151, "ухудшать": 205, "импонировать": 75, "осмыслить": 149, "преумножить": 8, "переоценивать": 65, "припоминать": 42, "обставить": 98, "подстраиваться": 102, "разоблачать": 143, "изобличать": 101, "кокетничать": 12, "загнивать": 13, "хлебнуть": 9, "умножить": 96, "расхваливать": 23, "отвоёвывать": 46, "культивировать": 101, "злоупотребить": 144, "тревожиться": 37, "влюбляться": 218, "сплачивать": 28, "дразнить": 116, "убавить": 20, "подшучивать": 77, "подыграть": 65, "разбомбить": 518, "окрылить": 9, "подкачать": 10, "приуныть": 6, "накричать": 87, "воодушевлять": 41, "вникнуть": 47, "здороваться": 85, "отравляться": 11, "утаивать": 49, "чахнуть": 6, "рукоплескать": 10, "ужасать": 20, "ужаснуть": 59, "втянуть": 198, "настигать": 23, "помёрзнуть": 4, "ладиться": 13, "высечь": 203, "присягнуть": 371, "пальнуть": 7, "скрасить": 36, "повреждаться": 32, "будоражить": 49, "зааплодировать": 16, "затерять": 5, "трепетать": 15, "излагать": 281, "ревновать": 46, "приболеть": 28, "расстраивать": 99, "порываться": 9, "приукрасить": 44, "добивать": 116, "выстрадать": 20, "ржать": 23, "сдохнуть": 60, "осквернять": 79, "полегчать": 16, "переступить": 128, "выгораживать": 24, "обижаться": 122, "прозевать": 20, "приискать": 6, "помучить": 6, "покарать": 79, "уяснить": 40, "втягивать": 100, "похорошеть": 12, "притупить": 11, "деморализовать": 71, "шефствовать": 13, "покрепчать": 4, "перебороть": 22, "уличать": 169, "тонизировать": 96, "просаживать": 5, "заволноваться": 16, "струхнуть": 5, "позорить": 208, "утроиться": 106, "утянуть": 14, "растранжирить": 4, "опорочить": 261, "нервировать": 38, "вдохновляться": 186, "обострить": 194, "затмевать": 45, "раскапывать": 66, "подсобить": 6, "терзать": 46, "вспугнуть": 15, "всполошить": 16, "флиртовать": 98, "отплатить": 34, "преувеличивать": 173, "истязать": 76, "клевать": 48, "оплакивать": 70, "разваливаться": 155, "молить": 108, "перестараться": 42, "подобать": 144, "перехитрить": 44, "раскачивать": 94, "подбивать": 21, "замочить": 35, "разлюбить": 30, "сглаживать": 37, "прозябать": 12, "подсовывать": 20, "переубедить": 85, "налаживаться": 111, "засветить": 31, "просадить": 5, "притуплять": 14, "сооружать": 123, "раскачать": 54, "отточить": 32, "жаловать": 19, "переполошиться": 6, "отпугнуть": 339, "унижаться": 14, "обрушиваться": 79, "благословлять": 68, "плевать": 161, "воздать": 75, "положиться": 80, "сразить": 50, "отступаться": 6, "обхитрить": 17, "поаплодировать": 29, "влепить": 23, "прельщать": 9, "пороть": 28, "выгородить": 26, "сотрясать": 56, "обдурить": 6, "наловить": 19, "уживаться": 36, "сколачивать": 4, "выпирать": 32, "деградировать": 107, "заигрывать": 61, "мазать": 30, "выпороть": 30, "помяться": 14, "стрельнуть": 9, "приказывать": 222, "поскандалить": 12, "теснить": 52, "вытряхнуть": 14, "мучиться": 80, "свыкнуться": 26, "сродниться": 3, "дозревать": 4, "струсить": 15, "обманываться": 9, "напугаться": 9, "крыть": 12, "досадить": 20, "отделать": 260, "уколоть": 29, "зевать": 31, "раскалываться": 11, "клеветать": 69, "насадить": 38, "вжиться": 56, "вывихнуть": 50, "насмехаться": 64, "ругнуться": 8, "угождать": 9, "перещеголять": 8, "хвалить": 208, "оболгать": 35, "разлагать": 70, "дезодорировать": 4, "возвеличивать": 11, "оздоровить": 59, "очернять": 65, "упиваться": 6, "корёжить": 3, "отклонять": 307, "наплевать": 97, "печалиться": 7, "удлиниться": 14, "затрястись": 15, "переубеждать": 8, "отодвигать": 60, "табуировать": 23, "удобрить": 6, "тосковать": 30, "схватывать": 13, "проболеть": 7, "прельстить": 6, "облаять": 9, "дезинформировать": 109, "досаждать": 57, "влачить": 12, "переволноваться": 16, "облапошить": 4, "принижать": 36, "поумнеть": 11, "воодушевиться": 16, "заездить": 10, "оттеснить": 673, "разладиться": 37, "затевать": 47, "задёргаться": 4, "побеспокоить": 17, "выдумывать": 67, "заботить": 102, "подкладывать": 51, "торпедировать": 85, "нажаловаться": 18, "подохнуть": 3, "истомиться": 2, "упокоиться": 11, "отдубасить": 3, "истончиться": 11, "поссорить": 115, "разоружить": 434, "сближать": 47, "поздороваться": 86, "изнашиваться": 26, "обрывать": 28, "вымазать": 26, "оскудевать": 4, "удлиняться": 14, "подкашивать": 2, "посотрудничать": 24, "настрадаться": 11, "умертвлять": 4, "постановлять": 52, "оканчиваться": 99, "нездоровиться": 8, "подучить": 16, "наставлять": 31, "выговаривать": 18, "подначивать": 16, "нахваливать": 12, "популяризовать": 57, "обличить": 22, "обесцениться": 193, "советоваться": 170, "ржаветь": 19, "боготворить": 16, "проедать": 24, "разукрашивать": 2, "третировать": 12, "завладевать": 25, "загонять": 138, "убавиться": 8, "завязываться": 73, "проглядеть": 14, "клеймить": 43, "разочаровывать": 86, "подмывать": 12, "натерпеться": 9, "заругаться": 2, "погрустить": 5, "осмысливать": 9, "гневить": 4, "противиться": 184, "спереть": 9, "раздосадовать": 77, "ладить": 69, "преумножиться": 2, "одаривать": 30, "наставать": 14, "охмурить": 3, "околеть": 8, "подурнеть": 2, "укорять": 9, "самоустраниться": 66, "ублажать": 12, "споить": 6, "заклеймить": 55, "испросить": 12, "урвать": 10, "разбаловать": 2, "разъяриться": 10, "приукрашивать": 19, "искоренять": 24, "скрадывать": 2, "стяжать": 8, "уничижать": 9, "удлинять": 30, "позволяться": 107, "прозреть": 17, "затрачивать": 80, "заржаветь": 17, "горевать": 33, "дописать": 107, "усвоить": 81, "сплачиваться": 10, "отнекиваться": 6, "стравливать": 37, "распугать": 34, "вникать": 58, "поклоняться": 113, "свергать": 41, "разучиться": 49, "обозлить": 17, "укокошить": 3, "узреть": 22, "перевоспитывать": 22, "истончаться": 15, "втянуться": 24, "сваливаться": 17, "смазывать": 21, "подкидывать": 34, "потеснить": 312, "задобрить": 28, "сгнивать": 4, "отшлифовать": 23, "отчитывать": 34, "нарадоваться": 4, "измучить": 12, "цапнуть": 5, "сознавать": 53, "главенствовать": 94, "опечалиться": 5, "породниться": 18, "пописать": 14, "освежать": 25, "потакать": 46, "обесцениваться": 38, "довлеть": 19, "разредить": 139, "недосмотреть": 8, "воспламенять": 15, "побаливать": 7, "поквитаться": 8, "досадовать": 6, "докопаться": 34, "познавать": 32, "транжирить": 6, "дурнеть": 26, "разъесть": 182, "утрачивать": 94, "спровадить": 2, "подбрасывать": 149, "сблизить": 104, "образумить": 21, "обелить": 41, "истреблять": 104, "издохнуть": 8, "рассмеяться": 108, "замарать": 13, "запротестовать": 17, "понадеяться": 348, "перегонять": 88, "задрожать": 14, "дёргаться": 44, "условиться": 162, "наорать": 14, "устрашать": 119, "расхохотаться": 11, "хохотать": 22, "обогащать": 237, "перенервничать": 19, "усовершенствоваться": 13, "очернить": 140, "измываться": 14, "вкатить": 4, "уповать": 45, "разнервничаться": 11, "попортить": 10, "проплакать": 6, "повергнуть": 90, "вымирать": 210, "разочароваться": 373, "воспламенить": 14, "торжествовать": 24, "расхищать": 16, "кончать": 95, "засохнуть": 27, "разболеться": 10, "упрятать": 19, "ужимать": 1, "любопытствовать": 20, "поплакать": 8, "выгорать": 33, "подружить": 16, "почить": 4, "вразумлять": 4, "осчастливить": 27, "закаляться": 14, "разобщить": 59, "увядать": 3, "измучиться": 2, "поддеть": 10, "созидать": 27, "лоббировать": 464, "восстать": 329, "апеллировать": 249, "истратить": 234, "приговаривать": 233, "плюнуть": 222, "саботировать": 198, "котироваться": 189, "эволюционировать": 184, "образовывать": 173, "подстрекать": 169, "воспротивиться": 164, "оборонять": 160, "инспирировать": 152, "осаждать": 137, "основывать": 125, "пленить": 125, "притеснять": 123, "сосуществовать": 121, "восхвалять": 120, "поиздеваться": 118, "пролоббировать": 113, "замазать": 112, "затравить": 106, "обосновываться": 104, "опозорить": 94, "согнать": 94, "линчевать": 91, "завязывать": 90, "забастовать": 87, "отучить": 86, "оттеснять": 86, "освистывать": 83, "воодушевить": 82, "удваиваться": 80, "перезаключить": 79, "ветировать": 78, "учреждать": 77, "измазать": 75, "искажаться": 73, "пронаблюдать": 72, "разломать": 71, "возненавидеть": 69, "предохранять": 69, "насаждать": 68, "попирать": 68, "разорять": 64, "потворствовать": 64, "устраниться": 64, "соблазнять": 63, "отыскивать": 63, "конструировать": 61, "стеречь": 61, "проспонсировать": 61, "отстраняться": 61, "интенсифицировать": 60, "подыгрывать": 58, "похвалиться": 58, "дёргать": 58, "рассорить": 57, "набрасываться": 56, "уверовать": 56, "угадывать": 53, "отстраниться": 52, "репрессировать": 52, "толковать": 52, "выкапывать": 50, "консолидироваться": 50, "разубедить": 49, "ослушаться": 48, "раскручиваться": 47, "раскалывать": 47, "воссоединить": 46, "отступиться": 46, "познать": 46, "дезорганизовать": 46, "развёртываться": 46, "преуменьшать": 45, "поколебать": 44, "принизить": 44, "воссоединяться": 43, "обеднеть": 42, "вламываться": 42, "присягать": 42, "надувать": 41, "губить": 41, "потешаться": 39, "корить": 39, "натравливать": 39, "сохнуть": 39, "обезглавливать": 39, "ассигновать": 39, "марать": 38, "высыхать": 38, "бесить": 37, "удваивать": 37, "глодать": 37, "ослабляться": 36, "разоружать": 35, "растлевать": 33, "вступаться": 33, "прослеживать": 33, "разочаровываться": 33, "патронировать": 33, "донимать": 32, "попустительствовать": 32, "одурачить": 31, "растрачивать": 31, "воспретить": 31, "расхитить": 31, "миловать": 31, "попенять": 30, "прислуживать": 30, "хулить": 30, "сердиться": 30, "расшатывать": 30, "отсоветовать": 29, "огорчиться": 29, "поучать": 29, "сгонять": 29, "восставать": 29, "надоедать": 29, "хихикать": 28, "стравить": 28, "проваливать": 27, "сквернословить": 27, "амортизировать": 27, "преуменьшить": 27, "пачкать": 27, "отвыкнуть": 27, "разваливать": 26, "разъедать": 26, "кончить": 26, "измельчать": 26, "растолковать": 26, "превозносить": 25, "умерщвлять": 25, "уязвить": 25, "надуваться": 25, "осмеять": 24, "ужиться": 24, "отвратить": 24, "одёрнуть": 23, "перевоспитать": 23, "кокнуть": 23, "раздражаться": 22, "поносить": 21, "подступить": 21, "дописывать": 21, "захоранивать": 21, "льстить": 21, "атрофироваться": 21, "переступать": 21, "перерождаться": 21, "сотрясти": 21, "затерроризировать": 20, "засмеять": 20, "дурачить": 20, "диссонировать": 20, "клеиться": 20, "возделывать": 19, "изводить": 19, "посмеиваться": 19, "хвалиться": 19, "исковеркать": 19, "возжелать": 18, "ухватить": 18, "перезаключать": 18, "беднеть": 18, "воздавать": 18, "оскорбляться": 17, "нагадить": 17, "преклоняться": 17, "утаскивать": 17, "разонравиться": 17, "подмочить": 17, "салютовать": 17, "расцветать": 16, "помереть": 16, "подкалывать": 16, "ввергать": 16, "перессориться": 16, "подколоть": 15, "обозлиться": 15, "подговаривать": 15, "наговаривать": 15, "укорачивать": 15, "кокать": 15, "вымарать": 15, "раскулачить": 14, "искушать": 14, "обмелеть": 14, "отрезвлять": 14, "беситься": 13, "удорожать": 13, "скооперироваться": 13, "повергать": 13, "сознать": 13, "переродиться": 13, "понуждать": 13, "распинать": 13, "укорить": 12, "пришивать": 12, "закалывать": 12, "воздвигать": 12, "обнищать": 12, "обставлять": 12, "подтрунивать": 12, "укорачиваться": 12, "выправиться": 12, "отучать": 12, "попрекнуть": 12, "предохранить": 12, "перерасходовать": 12, "выправляться": 12, "разбазаривать": 11, "выкрадывать": 11, "бедствовать": 11, "строчить": 11, "заискивать": 11, "вживаться": 11, "обезоруживать": 11, "разламывать": 11, "окультурить": 11, "исчерпывать": 11, "заморочить": 11, "огорчаться": 11, "упредить": 11, "турить": 11, "продувать": 11, "истолковывать": 11, "робеть": 11, "перебарщивать": 10, "дозволять": 10, "поругать": 10, "нищать": 10, "промотать": 10, "облажаться": 10, "коверкать": 10, "подстраховывать": 10, "зевнуть": 10, "приличествовать": 10, "обелять": 9, "зарыдать": 9, "затосковать": 9, "вырождаться": 9, "истощать": 9, "вызревать": 9, "приноровиться": 9, "доверяться": 9, "кооперироваться": 9, "страшиться": 9, "прикалываться": 9, "раскрутиться": 9, "зачинать": 9, "сникнуть": 9, "свистнуть": 9, "обожествлять": 8, "заарканить": 8, "загрустить": 8, "поубивать": 8, "изнывать": 8, "уделать": 8, "разубеждать": 8, "смаковать": 8, "расхвалить": 8, "доломать": 8, "одёргивать": 8, "убиться": 8, "чернить": 8, "подступиться": 8, "растревожить": 8, "породнить": 8, "осмыслять": 8, "испрашивать": 8, "мяться": 8, "оплакать": 8, "вянуть": 8, "дозволяться": 8, "подточить": 8, "подловить": 7, "прогневать": 7, "выродиться": 7, "исказиться": 7, "обжиться": 7, "самоустраняться": 7, "устрашить": 7, "возвеличить": 7, "подтачивать": 7, "надоумить": 7, "профукать": 7, "переловить": 7, "сагитировать": 7, "половить": 7, "увечить": 7, "застояться": 7, "попрекать": 6, "дохнуть": 6, "задабривать": 6, "подвигать": 6, "согрешить": 6, "дозреть": 6, "уняться": 6, "ёрничать": 6, "воспрещать": 6, "маяться": 6, "настучать": 6, "разреветься": 6, "переругаться": 6, "надуться": 6, "уесть": 6, "удорожить": 6, "мелеть": 6, "разболтать": 6, "редеть": 6, "поредеть": 6, "прирезать": 6, "наломать": 6, "похваляться": 6, "разбазарить": 6, "замучиться": 6, "рационализировать": 6, "разражаться": 6, "глупеть": 6, "перезреть": 6, "попереть": 6, "приучиться": 6, "разжевать": 6, "взгрустнуть": 5, "оплетать": 5, "напакостить": 5, "мучать": 5, "захлопать": 5, "изъесть": 5, "клясть": 5, "усечь": 5, "гоготать": 5, "взмолиться": 5, "загнить": 5, "ошельмовать": 5, "бесчестить": 5, "пятнать": 5, "истосковаться": 5, "перессорить": 5, "убояться": 5, "загнуться": 5, "мучаться": 5, "пережечь": 5, "тырить": 5, "запороть": 5, "просиять": 5, "проморгать": 5, "заветировать": 5, "разгневаться": 4, "наябедничать": 4, "побивать": 4, "киснуть": 4, "вскипеть": 4, "гневаться": 4, "заулыбаться": 4, "изломать": 4, "накидываться": 4, "поддевать": 4, "отлупить": 4, "плакаться": 4, "прошляпить": 4, "утраиваться": 4, "разругать": 4, "полечь": 4, "разламываться": 4, "дорастать": 4, "дегазировать": 4, "подтрунить": 4, "окрылять": 4, "воздаться": 4, "приканчивать": 4, "сердить": 4, "ссорить": 4, "самортизировать": 4, "подыхать": 4, "утраивать": 4, "возделать": 4, "преумножать": 4, "прихватывать": 4, "изничтожить": 4, "взволноваться": 4, "ослабиться": 4, "охаивать": 4, "обмануться": 4, "трусить": 4, "поколачивать": 4, "бранить": 4, "вскипать": 4, "закалиться": 4, "оздоровлять": 4, "воссоединять": 4, "озлобиться": 4, "поизноситься": 4, "восхвалить": 3, "раболепствовать": 3, "выискать": 3, "прельститься": 3, "похихикать": 3, "докапываться": 3, "коситься": 3, "выпроваживать": 3, "понастроить": 3, "проредить": 3, "захихикать": 3, "ужать": 3, "возрадоваться": 3, "покалывать": 3, "одурачивать": 3, "прорыдать": 3, "затюкать": 3, "оплести": 3, "брехать": 3, "возбранять": 3, "пакостить": 3, "зацеплять": 3, "науськивать": 3, "противоборствовать": 3, "долженствовать": 3, "хныкать": 3, "истончать": 3, "прикипеть": 3, "изукрасить": 3, "наобещать": 3, "уговориться": 3, "роптать": 3, "ославить": 3, "подступаться": 3, "выкраивать": 3, "нормализовывать": 3, "переругиваться": 3, "упреждать": 3, "захохотать": 3, "вызреть": 3, "вымазывать": 3, "утончаться": 3, "отрешиться": 3, "бахвалиться": 3, "подзадорить": 3, "напортить": 3, "застаиваться": 3, "тужить": 3, "трепать": 3, "прокиснуть": 3, "осрамить": 3, "регрессировать": 3, "собачиться": 3, "закиснуть": 3, "сыскать": 2, "приятельствовать": 2, "подворовывать": 2, "вымолить": 2, "изъедать": 2, "вмазать": 2, "обскакать": 2, "приспособляться": 2, "гильотинировать": 2, "допечь": 2, "надсмехаться": 2, "убавлять": 2, "загрызать": 2, "обхохотаться": 2, "разуверить": 2, "подсмеиваться": 2, "умнеть": 2, "кольнуть": 2, "хватануть": 2, "вымаливать": 2, "вздорить": 2, "приучаться": 2, "грызться": 2, "подлаживаться": 2, "либеральничать": 2, "упиться": 2, "зачахнуть": 2, "воодушевляться": 2, "захвалить": 2, "оборонить": 2, "дуться": 2, "облапошивать": 2, "сжиться": 2, "отвыкать": 2, "стопорить": 2, "умучить": 2, "уязвлять": 2, "жаться": 2, "заколебаться": 2, "перегорать": 2, "прогневить": 2, "раззадоривать": 2, "дубасить": 2, "свыкаться": 2, "тиснуть": 2, "убыстрять": 2, "обмельчать": 2, "шельмовать": 2, "вымарывать": 2, "преклониться": 2, "оттяпать": 2, "уяснять": 2, "засвечивать": 2, "отвращать": 2, "подзуживать": 2, "врубаться": 2, "рыпаться": 2, "отучиваться": 2, "мельчать": 2, "нагрешить": 2, "заныть": 2, "начхать": 2, "науськать": 2, "перехвалить": 2, "отсалютовать": 2, "поревновать": 2, "захапать": 2, "спаять": 2, "отваживать": 2, "ломить": 2, "осмеивать": 2, "истончить": 2, "извинять": 2, "передерживать": 2, "пресечься": 2, "разжёвывать": 2, "возблагодарить": 2, "зареветь": 2, "истрепать": 2, "загарпунить": 2, "передержать": 2, "натравлять": 2, "облаивать": 2, "изгаляться": 2, "проматывать": 2, "допекать": 2, "взбеленить": 1, "промучиться": 1, "отхватывать": 1, "подначить": 1, "лебезить": 1, "зауважать": 1, "сдрейфить": 1, "проворонить": 1, "накрасть": 1, "умаслить": 1, "хихикнуть": 1, "выпереть": 1, "побастовать": 1, "пригорюниться": 1, "поглупеть": 1, "насоздавать": 1, "разучиваться": 1, "умасливать": 1, "остерегать": 1, "отфинансировать": 1, "урывать": 1, "арканить": 1, "окрыляться": 1, "прореживать": 1, "устрашиться": 1, "костерить": 1, "приукрашать": 1, "хапать": 1, "подосадовать": 1, "вздорожать": 1, "поэксплуатировать": 1, "разобщиться": 1, "отплачивать": 1, "подстрекнуть": 1, "присоветовать": 1, "переспеть": 1, "пожухнуть": 1, "подрастерять": 1, "заржать": 1, "превознести": 1, "убыстрить": 1, "выслуживаться": 1, "ухлопать": 1, "окрылиться": 1, "срамить": 1, "предуведомить": 1, "терроризовать": 1, "отсмеяться": 1, "объегорить": 1, "осаживать": 1, "холуйствовать": 1, "разобидеться": 1, "намучиться": 1, "сцапать": 1, "пограбить": 1, "выпутать": 1, "перестреливаться": 1, "осерчать": 1, "растолковывать": 1, "ябедничать": 1, "занедужить": 1, "скисать": 1, "захваливать": 1, "прохлопать": 1, "кляузничать": 1, "отпарировать": 1, "покатываться": 1, "помучиться": 1, "потрафлять": 1, "задурить": 1, "стосковаться": 1, "приискивать": 1, "накостылять": 1, "дегенерировать": 1, "похохотать": 1, "полюбопытствовать": 1, "приколоться": 1, "обесславить": 1, "завянуть": 1, "хапнуть": 1, "поругивать": 1, "остервенеть": 1, "отбрить": 1, "отрешаться": 1, "возжаждать": 1, "соблазняться": 1, "прозревать": 1, "застращать": 1, "воздаваться": 1, "закисать": 1, "сломиться": 1, "заинтересовываться": 1, "уразуметь": 1, "напачкать": 1, "окультуривать": 1, "отучаться": 1, "просаботировать": 1, "застигать": 1, "вверяться": 1, "подхалимничать": 1, "выбранить": 1, "выпачкать": 1, "сражать": 1, "разграблять": 1, "нагнести": 1, "наподдать": 1, "вышучивать": 1, "оболванить": 1, "миндальничать": 1}